aukey/__init__.py
aukey/main.py
aukey-0.1.2.dist-info/LICENSE
aukey-0.1.2.dist-info/METADATA
aukey-0.1.2.dist-info/WHEEL
aukey-0.1.2.dist-info/top_level.txt
aukey-0.1.2.dist-info/RECORD
