Metadata-Version: 2.1
Name: aukey
Version: 0.1.2
Summary: A package for executing programs, files, websites by using shortcuts.
Author: Mostafa Mohamed Atef
License: MIT license
Keywords: aukey
License-File: LICENSE
Requires-Dist: keyboard
